[
  {
    "id": "359",
    "name": "Frax",
    "symbol": "FXS",
    "chain": "Multi-Chain",
    "audits": "2",
    "category": "Algo-Stables",
    "chains": [
      "Ethereum",
      "Fantom"
    ],
    "twitter": "fraxfinance",
    "oracles": [
      "Chainlink"
    ],
    "tvl": 1182065917.36099,
    "chainTvls": {
      "pool2": 24785233.952997636,
      "Ethereum-pool2": 24785233.952997636,
      "Ethereum-treasury": 143094224.7502251,
      "Ethereum": 1182019199.8934064,
      "Ethereum-staking": 259102137.53452772,
      "treasury": 143094224.7502251,
      "Fantom": 46717.467583681806,
      "staking": 259102137.53452772
    },
    "change_1h": -0.04,
    "change_1d": 0.05,
    "change_7d": -9.72,
    "staking": 259102137.53452772,
    "pool2": 24785233.952997636,
    "mcap": 423350190,
    "listedAt": 1623909947,
    "listedtimeago": "1 year ago",
    "rank": 1
  },
  {
    "id": "611",
    "name": "Neutrino",
    "symbol": "NSBT",
    "chain": "Waves",
    "audits": "2",
    "category": "Algo-Stables",
    "chains": [
      "Waves"
    ],
    "twitter": "neutrino_proto",
    "tvl": 69107645.581696,
    "chainTvls": {
      "Waves": 69107645.581696
    },
    "change_1h": -0.24,
    "change_1d": 3.05,
    "change_7d": -2.79,
    "mcap": 25722843,
    "listedAt": 1623909947,
    "listedtimeago": "1 year ago",
    "rank": 2
  },
  {
    "id": "427",
    "name": "Origin Dollar",
    "symbol": "OGV",
    "chain": "Ethereum",
    "audits": "2",
    "category": "Algo-Stables",
    "chains": [
      "Ethereum"
    ],
    "twitter": "OriginProtocol",
    "tvl": 48539523.390456095,
    "chainTvls": {
      "Ethereum": 48539523.390456095,
      "Ethereum-staking": 11958706.823417198,
      "staking": 11958706.823417198
    },
    "change_1h": -0.04,
    "change_1d": -0.01,
    "change_7d": 0.1,
    "staking": 11958706.823417198,
    "mcap": 3719090,
    "listedAt": 1623909947,
    "listedtimeago": "1 year ago",
    "rank": 3
  },
  {
    "id": "376",
    "name": "Tomb Finance",
    "symbol": "TOMB",
    "chain": "Fantom",
    "audits": "3",
    "category": "Algo-Stables",
    "chains": [
      "Fantom"
    ],
    "twitter": "tombfinance",
    "oracles": [
      "DIA"
    ],
    "tvl": 28185343.013118602,
    "chainTvls": {
      "pool2": 2200677.767179725,
      "Fantom-staking": 11081210.075349506,
      "Fantom-pool2": 2200677.767179725,
      "staking": 11081210.075349506,
      "Fantom": 28185343.013118602
    },
    "change_1h": -0.42,
    "change_1d": 1.02,
    "change_7d": -16.02,
    "staking": 11081210.075349506,
    "pool2": 2200677.767179725,
    "mcap": 14007681,
    "listedAt": 1623909947,
    "listedtimeago": "1 year ago",
    "rank": 4
  },
  {
    "id": "1402",
    "name": "UXD",
    "symbol": "UXP",
    "chain": "Solana",
    "audits": "2",
    "category": "Algo-Stables",
    "chains": [
      "Solana"
    ],
    "twitter": "UXDProtocol",
    "language": "Rust",
    "listedAt": 1644696944,
    "openSource": false,
    "tvl": 14999898.561665,
    "chainTvls": {
      "Solana": 14999898.561665
    },
    "change_1h": 0,
    "change_1d": -0.1,
    "change_7d": -12.26,
    "mcap": 7490424,
    "listedtimeago": "6 months ago",
    "rank": 5
  },
  {
    "id": "195",
    "name": "DefiDollar DAO",
    "symbol": "DFD",
    "chain": "Ethereum",
    "audits": "2",
    "category": "Algo-Stables",
    "chains": [
      "Ethereum"
    ],
    "twitter": "defidollar",
    "oracles": [
      "Chainlink"
    ],
    "tvl": 12200614.130696293,
    "chainTvls": {
      "Ethereum": 12200614.130696293
    },
    "change_1h": -0.31,
    "change_1d": 2.1,
    "change_7d": -12.08,
    "mcap": 474572,
    "listedAt": 1623909947,
    "listedtimeago": "1 year ago",
    "rank": 6
  },
  {
    "id": "1194",
    "name": "Sperax USD",
    "symbol": "USDs",
    "chain": "Multi-Chain",
    "audits": "2",
    "category": "Algo-Stables",
    "chains": [
      "Arbitrum",
      "Ethereum"
    ],
    "twitter": "SperaxUSD",
    "oracles": [
      "DIA"
    ],
    "listedAt": 1641400651,
    "tvl": 4266875.863573143,
    "chainTvls": {
      "Ethereum": 0,
      "Ethereum-staking": 221972.359708245,
      "Arbitrum-staking": 1633559.9404899538,
      "Arbitrum": 4266875.863573143,
      "staking": 1855532.3001981988
    },
    "change_1h": 0.0,
    "change_1d": 0.38,
    "change_7d": 11.78,
    "staking": 1855532.3001981988,
    "mcap": 25521598,
    "listedtimeago": "8 months ago",
    "rank": 7
  },
  {
    "id": "1261",
    "name": "DarkCrypto",
    "symbol": "DARK",
    "chain": "Cronos",
    "audits": "2",
    "category": "Algo-Stables",
    "chains": [
      "Cronos"
    ],
    "twitter": "DarkCryptoFi",
    "forkedFrom": [
      "Tomb Finance"
    ],
    "listedAt": 1642192171,
    "tvl": 966042.8040265684,
    "chainTvls": {
      "Cronos": 966042.8040265684,
      "pool2": 315429.62201752496,
      "Cronos-pool2": 315429.62201752496,
      "Cronos-staking": 7323.799392869224,
      "staking": 7323.799392869224
    },
    "change_1h": -0.3,
    "change_1d": -8.98,
    "change_7d": -16.07,
    "staking": 7323.799392869224,
    "pool2": 315429.62201752496,
    "mcap": 874802,
    "listedtimeago": "7 months ago",
    "rank": 8
  },
  {
    "id": "1811",
    "name": "Spice Trade",
    "symbol": "SPICE",
    "chain": "Multi-Chain",
    "audits": "0",
    "category": "Algo-Stables",
    "chains": [
      "Ethereum",
      "Avalanche",
      "Binance",
      "Polygon"
    ],
    "oracles": [],
    "forkedFrom": [],
    "twitter": "spicetradeai",
    "listedAt": 1654678696,
    "tvl": 909220.4097694277,
    "chainTvls": {
      "pool2": 64673.98411266936,
      "Polygon-pool2": 15389.982503156036,
      "Binance-pool2": 0,
      "Ethereum-pool2": 4378.991633642924,
      "Binance": 216990.09209779176,
      "Ethereum": 419826.1615713137,
      "Binance-staking": 0.47560301191396065,
      "Avalanche": 268541.7073603823,
      "Avalanche-staking": 933.4312820154511,
      "Ethereum-staking": 162.09082312608615,
      "Polygon": 3862.448739940037,
      "Polygon-staking": 1153.104678084725,
      "Avalanche-pool2": 44905.009975870395,
      "staking": 2249.102386238176
    },
    "change_1h": 0.15,
    "change_1d": 1.16,
    "change_7d": -21.28,
    "staking": 2249.102386238176,
    "pool2": 64673.98411266936,
    "mcap": 8809.45,
    "listedtimeago": "3 months ago",
    "rank": 9
  },
  {
    "id": "2065",
    "name": "Chocodoge",
    "symbol": "USCD",
    "chain": "Dogechain",
    "audits": "0",
    "category": "Algo-Stables",
    "chains": [
      "Dogechain"
    ],
    "oracles": [
      "TWAP"
    ],
    "forkedFrom": [
      "Tomb Fiannce"
    ],
    "twitter": "ChocoDoge_",
    "listedAt": 1662470738,
    "tvl": 631322.5999392176,
    "chainTvls": {
      "Dogechain": 631322.5999392176,
      "Dogechain-pool2": 74997.27869394972,
      "pool2": 74997.27869394972,
      "Dogechain-staking": 0,
      "staking": 0
    },
    "change_1h": -13.0,
    "change_1d": -6.19,
    "change_7d": null,
    "staking": 0,
    "pool2": 74997.27869394972,
    "listedtimeago": "1 day ago",
    "rank": 10
  },
  {
    "id": "1794",
    "name": "Ostable",
    "symbol": "-",
    "chain": "Obyte",
    "audits": "0",
    "category": "Algo-Stables",
    "chains": [
      "Obyte"
    ],
    "oracles": [],
    "forkedFrom": [],
    "twitter": "ObyteOrg",
    "listedAt": 1653984585,
    "tvl": 446324.9249892474,
    "chainTvls": {
      "Obyte": 446324.9249892474
    },
    "change_1h": -0.26,
    "change_1d": 1.15,
    "change_7d": -0.19,
    "listedtimeago": "3 months ago",
    "rank": 11
  },
  {
    "id": "1233",
    "name": "Creditum",
    "symbol": "CREDIT",
    "chain": "Fantom",
    "audits": "0",
    "category": "Algo-Stables",
    "chains": [
      "Fantom"
    ],
    "twitter": "RevenantLabs",
    "listedAt": 1641878060,
    "tvl": 421124.077296405,
    "chainTvls": {
      "pool2": 40405.931339099654,
      "Fantom-staking": 5749.489292402208,
      "Fantom-pool2": 40405.931339099654,
      "staking": 5749.489292402208,
      "Fantom": 421124.077296405
    },
    "change_1h": -0.04,
    "change_1d": 0.04,
    "change_7d": 0.11,
    "staking": 5749.489292402208,
    "pool2": 40405.931339099654,
    "mcap": 0,
    "listedtimeago": "7 months ago",
    "rank": 12
  },
  {
    "id": "356",
    "name": "Dopple Finance",
    "symbol": "DOP",
    "chain": "Multi-Chain",
    "audits": "2",
    "category": "Algo-Stables",
    "chains": [
      "Binance",
      "Fantom",
      "Harmony"
    ],
    "twitter": "dopplefi",
    "tvl": 391857.3465840275,
    "chainTvls": {
      "Binance": 391699.6363681107,
      "Harmony": 3.0546773468974524,
      "Fantom": 154.65553856988876
    },
    "change_1h": -0.04,
    "change_1d": 0.01,
    "change_7d": 0.33,
    "mcap": 0,
    "listedAt": 1623909947,
    "listedtimeago": "1 year ago",
    "rank": 13
  },
  {
    "id": "169",
    "name": "Basis Cash",
    "symbol": "BAC",
    "chain": "Ethereum",
    "audits": "2",
    "category": "Algo-Stables",
    "chains": [
      "Ethereum"
    ],
    "twitter": "BasisCash",
    "tvl": 329268.0043046291,
    "chainTvls": {
      "Ethereum": 329268.0043046291
    },
    "change_1h": -0.04,
    "change_1d": -0.03,
    "change_7d": 0.13,
    "mcap": 254991,
    "listedAt": 1623909947,
    "listedtimeago": "1 year ago",
    "rank": 14
  },
  {
    "id": "1226",
    "name": "Oin Finance",
    "symbol": "OIN",
    "chain": "Multi-Chain",
    "audits": "2",
    "category": "Algo-Stables",
    "chains": [
      "Ethereum",
      "Near",
      "Harmony"
    ],
    "twitter": "FinanceOin",
    "oracles": [
      "DIA"
    ],
    "listedAt": 1641873083,
    "tvl": 261174.85127479164,
    "chainTvls": {
      "Ethereum": 141360.95019647147,
      "pool2": 18846.67360436437,
      "Near": 70297.73837845105,
      "Harmony": 49516.16269986912,
      "Ethereum-pool2": 18846.67360436437
    },
    "change_1h": -0.17,
    "change_1d": 6.11,
    "change_7d": 0.46,
    "pool2": 18846.67360436437,
    "mcap": 350241,
    "listedtimeago": "7 months ago",
    "rank": 15
  },
  {
    "id": "255",
    "name": "Fei Protocol",
    "symbol": "FEI",
    "chain": "Ethereum",
    "audits": "2",
    "category": "Algo-Stables",
    "chains": [
      "Ethereum"
    ],
    "twitter": "feiprotocol",
    "oracles": [
      "Chainlink"
    ],
    "tvl": 192005.5158105246,
    "chainTvls": {
      "Ethereum": 192005.5158105246
    },
    "change_1h": -0.52,
    "change_1d": -2.54,
    "change_7d": -4.48,
    "mcap": 521800599,
    "listedAt": 1623909947,
    "listedtimeago": "1 year ago",
    "rank": 16
  },
  {
    "id": "1279",
    "name": "Tulip",
    "symbol": "TULIP",
    "chain": "Oasis",
    "audits": "0",
    "category": "Algo-Stables",
    "chains": [
      "Oasis"
    ],
    "twitter": "MoneyTulip",
    "oracles": [
      "TWAP"
    ],
    "forkedFrom": [
      "Tomb Finance"
    ],
    "listedAt": 1642456433,
    "tvl": 168065.73004021152,
    "chainTvls": {
      "Oasis": 168065.73004021152,
      "Oasis-staking": 0,
      "staking": 0
    },
    "change_1h": -0.24,
    "change_1d": 3.29,
    "change_7d": -3.99,
    "staking": 0,
    "listedtimeago": "7 months ago",
    "rank": 17
  },
  {
    "id": "702",
    "name": "Coffin Finance",
    "symbol": "COFFIN",
    "chain": "Fantom",
    "audits": "2",
    "category": "Algo-Stables",
    "chains": [
      "Fantom"
    ],
    "twitter": "CoffinFinance",
    "listedAt": 1635104456,
    "tvl": 127353.29592818477,
    "chainTvls": {
      "Fantom-staking": 1016.9528900438216,
      "staking": 1016.9528900438216,
      "Fantom": 127353.29592818477
    },
    "change_1h": -0.12,
    "change_1d": 0.69,
    "change_7d": -1.11,
    "staking": 1016.9528900438216,
    "mcap": 0,
    "listedtimeago": "10 months ago",
    "rank": 18
  },
  {
    "id": "1920",
    "name": "OrderNChaos",
    "symbol": "CHAOS",
    "chain": "Avalanche",
    "audits": "0",
    "category": "Algo-Stables",
    "chains": [
      "Avalanche"
    ],
    "oracles": [],
    "forkedFrom": [],
    "twitter": "ordernchaos_fi",
    "listedAt": 1658736615,
    "tvl": 117943.18945050449,
    "chainTvls": {
      "Avalanche": 117943.18945050449
    },
    "change_1h": -0.0,
    "change_1d": -0.09,
    "change_7d": -0.58,
    "listedtimeago": "1 month ago",
    "rank": 19
  },
  {
    "id": "1277",
    "name": "Paprprintr",
    "symbol": "PAPR",
    "chain": "Multi-Chain",
    "audits": "2",
    "category": "Algo-Stables",
    "chains": [
      "Binance",
      "Kucoin",
      "Polygon",
      "Fantom",
      "Aurora",
      "OKExChain"
    ],
    "twitter": "paprprintr",
    "forkedFrom": [
      "Basis Cash"
    ],
    "listedAt": 1642453213,
    "tvl": 50310.669495999995,
    "chainTvls": {
      "Fantom-staking": 219.772408,
      "Polygon-pool2": 7365.124235,
      "Aurora-pool2": 2008.185877,
      "Binance-pool2": 14967.970633,
      "Binance": 21228.213769,
      "Binance-staking": 5253.60538,
      "Kucoin-pool2": 674.935071,
      "Fantom": 1553.863687,
      "staking": 6533.030662,
      "Aurora-staking": 41.940688,
      "OKExChain-staking": 0,
      "OKExChain": 23.756375,
      "pool2": 26472.51597,
      "Kucoin": 19106.980707,
      "Aurora": 1346.449722,
      "Kucoin-staking": 19.772589,
      "Polygon": 7051.405236,
      "Polygon-staking": 997.939597,
      "Fantom-pool2": 1456.300154,
      "OKExChain-pool2": 0
    },
    "change_1h": 0.02,
    "change_1d": 1.38,
    "change_7d": -5.79,
    "staking": 6533.030662,
    "pool2": 26472.51597,
    "mcap": 0,
    "listedtimeago": "7 months ago",
    "rank": 20
  },
  {
    "id": "1680",
    "name": "Orcus Finance",
    "symbol": "ORU",
    "chain": "Astar",
    "audits": "2",
    "category": "Algo-Stables",
    "chains": [
      "Astar"
    ],
    "oracles": [
      "DIA"
    ],
    "forkedFrom": [],
    "twitter": "Orcus_Finance",
    "listedAt": 1650838812,
    "tvl": 46261.995071072386,
    "chainTvls": {
      "Astar-pool2": 15902.666597316267,
      "Astar": 46261.995071072386,
      "pool2": 15902.666597316267,
      "Astar-staking": 0,
      "staking": 0
    },
    "change_1h": -0.04,
    "change_1d": 0.04,
    "change_7d": 0.14,
    "staking": 0,
    "pool2": 15902.666597316267,
    "listedtimeago": "4 months ago",
    "rank": 21
  },
  {
    "id": "1080",
    "name": "XUSD Money",
    "symbol": "XUSD",
    "chain": "Ethereum",
    "audits": "0",
    "category": "Algo-Stables",
    "chains": [
      "Ethereum"
    ],
    "twitter": "xusd_stable",
    "forkedFrom": [
      "Frax"
    ],
    "listedAt": 1640222404,
    "tvl": 27399.168337402625,
    "chainTvls": {
      "Ethereum": 27399.168337402625,
      "pool2": 1291.1383763355761,
      "Ethereum-staking": 0,
      "staking": 0,
      "Ethereum-pool2": 1291.1383763355761
    },
    "change_1h": -0.34,
    "change_1d": 1.89,
    "change_7d": 2.3,
    "staking": 0,
    "pool2": 1291.1383763355761,
    "listedtimeago": "8 months ago",
    "rank": 22
  },
  {
    "id": "1827",
    "name": "SaharaDAO",
    "symbol": "MNG",
    "chain": "Cronos",
    "audits": "2",
    "category": "Algo-Stables",
    "chains": [
      "Cronos"
    ],
    "oracles": [
      "Chainlink"
    ],
    "forkedFrom": [
      "Fantasm"
    ],
    "twitter": "SaharaDao",
    "listedAt": 1655464683,
    "tvl": 24525.953177940602,
    "chainTvls": {
      "Cronos": 24525.953177940602,
      "pool2": 45490.10966586838,
      "Cronos-pool2": 45490.10966586838,
      "Cronos-staking": 21271.78663188882,
      "staking": 21271.78663188882
    },
    "change_1h": -0.12,
    "change_1d": -1.31,
    "change_7d": -52.1,
    "staking": 21271.78663188882,
    "pool2": 45490.10966586838,
    "mcap": 0,
    "listedtimeago": "2 months ago",
    "rank": 23
  },
  {
    "id": "1504",
    "name": "Fantasm",
    "symbol": "FSM",
    "chain": "Fantom",
    "audits": "0",
    "category": "Algo-Stables",
    "chains": [
      "Fantom"
    ],
    "oracles": [
      "Chainlink"
    ],
    "forkedFrom": [],
    "twitter": "fantasm_finance",
    "listedAt": 1646391958,
    "tvl": 16910.958377549177,
    "chainTvls": {
      "pool2": 11712.443918066505,
      "Fantom-staking": 6128.362722331076,
      "Fantom-pool2": 11712.443918066505,
      "staking": 6128.362722331076,
      "Fantom": 16910.958377549177
    },
    "change_1h": -0.49,
    "change_1d": 3.57,
    "change_7d": -7.18,
    "staking": 6128.362722331076,
    "pool2": 11712.443918066505,
    "mcap": 0,
    "listedtimeago": "6 months ago",
    "rank": 24
  },
  {
    "id": "1610",
    "name": "Pegasusdollar",
    "symbol": "PES",
    "chain": "Cronos",
    "audits": "2",
    "category": "Algo-Stables",
    "chains": [
      "Cronos"
    ],
    "oracles": [
      "TWAP"
    ],
    "forkedFrom": [
      "Tomb Finance"
    ],
    "twitter": "pegasusdollar",
    "listedAt": 1649105294,
    "tvl": 16873.596672268523,
    "chainTvls": {
      "Cronos": 16873.596672268523,
      "pool2": 155717.08651489855,
      "Cronos-pool2": 155717.08651489855,
      "Cronos-staking": 1518.6836940147164,
      "staking": 1518.6836940147164
    },
    "change_1h": -0.05,
    "change_1d": -0.41,
    "change_7d": -5.92,
    "staking": 1518.6836940147164,
    "pool2": 155717.08651489855,
    "listedtimeago": "5 months ago",
    "rank": 25
  },
  {
    "id": "1528",
    "name": "Blindex",
    "symbol": "BDX",
    "chain": "RSK",
    "audits": "2",
    "category": "Algo-Stables",
    "chains": [
      "RSK"
    ],
    "oracles": [
      "Internal"
    ],
    "forkedFrom": [
      "Frax"
    ],
    "twitter": "BlinDEXio",
    "listedAt": 1646949250,
    "tvl": 14113.045902685124,
    "chainTvls": {
      "RSK": 14113.045902685124
    },
    "change_1h": -0.54,
    "change_1d": 3.88,
    "change_7d": 3.61,
    "listedtimeago": "5 months ago",
    "rank": 26
  },
  {
    "id": "1483",
    "name": "V3S Finance",
    "symbol": "V3S",
    "chain": "Cronos",
    "audits": "0",
    "category": "Algo-Stables",
    "chains": [
      "Cronos"
    ],
    "oracles": [],
    "forkedFrom": [
      "Tomb Finance"
    ],
    "twitter": "v3sfinance",
    "listedAt": 1646099642,
    "tvl": 14033.304443073785,
    "chainTvls": {
      "Cronos": 14033.304443073785,
      "pool2": 275593.6377762294,
      "Cronos-pool2": 275593.6377762294,
      "Cronos-staking": 407863.7595648853,
      "staking": 407863.7595648853
    },
    "change_1h": -0.1,
    "change_1d": -5.22,
    "change_7d": -11.23,
    "staking": 407863.7595648853,
    "pool2": 275593.6377762294,
    "listedtimeago": "6 months ago",
    "rank": 27
  },
  {
    "id": "1019",
    "name": "OpenDAO",
    "symbol": "pOPEN",
    "chain": "Multi-Chain",
    "audits": "2",
    "category": "Algo-Stables",
    "chains": [
      "Ethereum",
      "Binance"
    ],
    "twitter": "opendaoprotocol",
    "listedAt": 1639418306,
    "forkedFrom": [
      "Compound"
    ],
    "tvl": 12719.68718969412,
    "chainTvls": {
      "Binance": 3674.9283500988686,
      "Ethereum": 9044.758839595252,
      "pool2": 7021.279717013471,
      "Ethereum-pool2": 7021.279717013471
    },
    "change_1h": 0.04,
    "change_1d": 0.67,
    "change_7d": 0.45,
    "pool2": 7021.279717013471,
    "mcap": 54667,
    "listedtimeago": "8 months ago",
    "rank": 28
  },
  {
    "id": "1182",
    "name": "ChargeDeFi",
    "symbol": "CHARGE",
    "chain": "Binance",
    "audits": "2",
    "category": "Algo-Stables",
    "chains": [
      "Binance"
    ],
    "twitter": "ChargeDeFi",
    "listedAt": 1641195222,
    "tvl": 5912.859261320482,
    "chainTvls": {
      "Binance": 5912.859261320482,
      "Binance-staking": 24219.169030957746,
      "pool2": 54171.732307349834,
      "Binance-pool2": 54171.732307349834,
      "staking": 24219.169030957746
    },
    "change_1h": -0.05,
    "change_1d": 0.12,
    "change_7d": 10.77,
    "staking": 24219.169030957746,
    "pool2": 54171.732307349834,
    "mcap": 0,
    "listedtimeago": "8 months ago",
    "rank": 29
  },
  {
    "id": "1915",
    "name": "Nava finance",
    "symbol": "NAVA",
    "chain": "REI",
    "audits": "0",
    "category": "Algo-Stables",
    "chains": [
      "REI"
    ],
    "oracles": [],
    "forkedFrom": [
      "Tomb Finance"
    ],
    "twitter": "navafinance",
    "listedAt": 1658332788,
    "tvl": 3964.3252063251443,
    "chainTvls": {
      "pool2": 11170.301746480776,
      "REI": 3964.3252063251443,
      "REI-pool2": 11170.301746480776,
      "REI-staking": 231.35364765427587,
      "staking": 231.35364765427587
    },
    "change_1h": -0.41,
    "change_1d": 3.94,
    "change_7d": -70.29,
    "staking": 231.35364765427587,
    "pool2": 11170.301746480776,
    "listedtimeago": "1 month ago",
    "rank": 30
  },
  {
    "id": "1413",
    "name": "Savanna Finance",
    "symbol": "SVN",
    "chain": "Cronos",
    "audits": "2",
    "category": "Algo-Stables",
    "chains": [
      "Cronos"
    ],
    "oracles": [],
    "forkedFrom": [
      "Tomb Finance"
    ],
    "twitter": "MMFcrypto",
    "parentProtocol": "MM Finance",
    "listedAt": 1644884068,
    "tvl": 2976.7640898438235,
    "chainTvls": {
      "Cronos": 2976.7640898438235,
      "pool2": 2341683.701853226,
      "Cronos-pool2": 2341683.701853226,
      "Cronos-staking": 1667720.8184750427,
      "staking": 1667720.8184750427
    },
    "change_1h": -0.64,
    "change_1d": -0.36,
    "change_7d": -15.16,
    "staking": 1667720.8184750427,
    "pool2": 2341683.701853226,
    "mcap": 4560451,
    "listedtimeago": "6 months ago",
    "rank": 31
  },
  {
    "id": "1259",
    "name": "Pillar",
    "symbol": "-",
    "chain": "Zilliqa",
    "audits": "0",
    "category": "Algo-Stables",
    "chains": [
      "Zilliqa"
    ],
    "twitter": "DevPillar",
    "listedAt": 1642144681,
    "tvl": 2754.529485759792,
    "chainTvls": {
      "Zilliqa": 2754.529485759792
    },
    "change_1h": -0.27,
    "change_1d": 2.32,
    "change_7d": -4.02,
    "listedtimeago": "7 months ago",
    "rank": 32
  }
]