[
  {
    "id": "2",
    "name": "WBTC",
    "symbol": "WBTC",
    "chain": "Ethereum",
    "audits": "2",
    "category": "Bridge",
    "chains": [
      "Ethereum"
    ],
    "twitter": "WrappedBTC",
    "oracles": [],
    "tvl": 5253582617.613532,
    "chainTvls": {
      "Ethereum": 5253582617.613532
    },
    "change_1h": 0.26,
    "change_1d": 5.32,
    "change_7d": 3.19,
    "mcap": 5253504223,
    "listedAt": 1623909947,
    "listedtimeago": "1 year ago",
    "rank": 1
  },
  {
    "id": "694",
    "name": "JustCryptos",
    "symbol": "JST",
    "chain": "Tron",
    "audits": "0",
    "category": "Bridge",
    "chains": [
      "Tron"
    ],
    "twitter": "DeFi_JUST",
    "listedAt": 1634850489,
    "tvl": 2558079776,
    "chainTvls": {
      "Tron": 2558079776
    },
    "change_1h": 0.2,
    "change_1d": 5.36,
    "change_7d": 3.31,
    "listedtimeago": "1 year ago",
    "rank": 2
  },
  {
    "id": "591",
    "name": "Multichain",
    "symbol": "MULTI",
    "chain": "Multi-Chain",
    "audits": "2",
    "category": "Bridge",
    "chains": [
      "Fantom",
      "Ethereum",
      "Binance",
      "Moonriver",
      "Polygon",
      "Avalanche",
      "Optimism",
      "Kava",
      "Moonbeam",
      "OKExChain",
      "Arbitrum",
      "Dogechain",
      "Cronos",
      "Milkomeda",
      "IoTeX",
      "Kucoin",
      "Telos",
      "Metis",
      "xDai",
      "Harmony",
      "Velas",
      "Conflux",
      "Bittorrent",
      "EthereumPoW",
      "Celo",
      "Syscoin",
      "Bitgert",
      "Heco",
      "Kardia",
      "Shiden",
      "Oasis",
      "Boba",
      "Fuse",
      "Fusion",
      "EthereumClassic",
      "REI",
      "Evmos",
      "CLV",
      "ThunderCore",
      "RSK",
      "Astar",
      "Milkomeda A1",
      "smartBCH",
      "GodwokenV1",
      "Arbitrum Nova",
      "Ronin",
      "OntologyEVM",
      "Klaytn",
      "DFK",
      "Cube",
      "TomoChain",
      "Hoo",
      "Aurora"
    ],
    "twitter": "MultichainOrg",
    "tvl": 1516285498.1743715,
    "chainTvls": {
      "Optimism": 33722861.251636565,
      "DFK": 0,
      "Cube": 0,
      "Harmony": 1720142.5474648513,
      "ThunderCore": 20165.804239700767,
      "CLV": 56387.137655170394,
      "Binance": 167480629.4293888,
      "Dogechain": 7608704.843130282,
      "Astar": 8889.509454506937,
      "Oasis": 528566.268037797,
      "Heco": 778136.5405531212,
      "Shiden": 586508.2670553928,
      "Avalanche": 41009985.21532202,
      "Telos": 2514136.7101177694,
      "Arbitrum": 14443526.4857971,
      "Milkomeda A1": 3841.6764517432,
      "TomoChain": 0,
      "Evmos": 56458.56120897702,
      "Hoo": 0,
      "Arbitrum Nova": 762.8769666504,
      "Milkomeda": 4087832.4498678623,
      "smartBCH": 3133.824060846693,
      "RSK": 17236.736436151914,
      "Moonbeam": 22044480.698473543,
      "Aurora": 0,
      "EthereumPoW": 1115535.7548629367,
      "Polygon": 49116647.93752723,
      "OntologyEVM": 37.2953002,
      "Metis": 2482186.4081059056,
      "Kava": 23470559.366735965,
      "Moonriver": 63729674.47250098,
      "Klaytn": 23.582916,
      "Velas": 1437167.2434716779,
      "Bitgert": 970017.0728665286,
      "IoTeX": 3854895.2376742223,
      "Ethereum": 288596298.2059534,
      "xDai": 2171297.56352533,
      "EthereumClassic": 104807.62057185045,
      "Conflux": 1296850.4668752372,
      "GodwokenV1": 911.4594753839909,
      "Celo": 1026262.5945004642,
      "Fuse": 195218.64394626525,
      "Fusion": 188953.4130720418,
      "Fantom": 752777839.3535024,
      "Cronos": 4972471.17465818,
      "OKExChain": 20474578.846417066,
      "Kardia": 636576.9897698665,
      "Kucoin": 3382349.931540049,
      "Bittorrent": 1217659.312118422,
      "Boba": 259787.04712080833,
      "Syscoin": 1017549.7773865043,
      "REI": 81018.11261965001,
      "Ronin": 58.872916
    },
    "change_1h": 0.8,
    "change_1d": 1.83,
    "change_7d": 1.12,
    "mcap": 0,
    "listedAt": 1623909947,
    "listedtimeago": "1 year ago",
    "rank": 3
  },
  {
    "id": "1541",
    "name": "Portal",
    "symbol": "-",
    "chain": "Multi-Chain",
    "audits": "2",
    "category": "Bridge",
    "chains": [
      "Ethereum",
      "Terra",
      "Solana",
      "Near",
      "Binance",
      "Polygon",
      "Avalanche",
      "Fantom",
      "Celo",
      "Aurora",
      "Oasis",
      "Karura",
      "Aptos",
      "Acala",
      "Terra2",
      "Moonbeam",
      "Klaytn",
      "Algorand"
    ],
    "oracles": [],
    "forkedFrom": [],
    "twitter": "portalbridge_",
    "listedAt": 1647148275,
    "tvl": 555760263.75,
    "chainTvls": {
      "Karura": 116811.55,
      "Klaytn": 108.76,
      "Binance": 21015505.64,
      "Ethereum": 405255080.42,
      "Oasis": 178924.59,
      "Avalanche": 12891594.13,
      "Celo": 1360212.62,
      "Fantom": 1722100.35,
      "Aptos": 86735.07,
      "Terra": 41099270.97,
      "Near": 26397606.01,
      "Acala": 4056.11,
      "Moonbeam": 280.21,
      "Aurora": 1303166.62,
      "Algorand": 0.45,
      "Polygon": 15657176.22,
      "Solana": 28669980.16,
      "Terra2": 1653.35
    },
    "change_1h": -0.01,
    "change_1d": 17.58,
    "change_7d": 8.56,
    "listedtimeago": "7 months ago",
    "rank": 4
  },
  {
    "id": "1796",
    "name": "Poly Network",
    "symbol": "-",
    "chain": "Multi-Chain",
    "audits": "2",
    "category": "Bridge",
    "chains": [
      "Ethereum",
      "Binance",
      "NEO",
      "Heco",
      "Ontology",
      "Neo3",
      "Polygon",
      "Arbitrum",
      "Optimism",
      "Avalanche",
      "Fantom",
      "Metis",
      "Boba",
      "Celo",
      "xDai",
      "Kava",
      "OKExChain",
      "Starcoin",
      "Harmony",
      "Carbon",
      "CLV",
      "Astar",
      "Oasis",
      "Pallete",
      "Conflux",
      "Zilliqa",
      "Hoo",
      "Kucoin",
      "Bytomsidechain"
    ],
    "oracles": [],
    "forkedFrom": [],
    "twitter": "PolyNetwork2",
    "listedAt": 1654083965,
    "tvl": 326787393.06,
    "chainTvls": {
      "Optimism": 603546.83,
      "Metis": 188299.23,
      "Kava": 14319.3,
      "Ontology": 3491521.42,
      "Harmony": 0,
      "Carbon": 0,
      "CLV": 0,
      "Binance": 42950883.96,
      "Ethereum": 221667175.52,
      "xDai": 40804.74,
      "Astar": 0,
      "Oasis": 0,
      "Heco": 20701589.62,
      "Avalanche": 408333.68,
      "Pallete": 0,
      "Conflux": 0,
      "Celo": 76017.59,
      "Arbitrum": 1228209.75,
      "Starcoin": 15.53,
      "Neo3": 2709702.31,
      "Fantom": 353766.57,
      "OKExChain": 1365.26,
      "Zilliqa": 0,
      "Hoo": 0,
      "Kucoin": 0,
      "Boba": 101281.21,
      "Bytomsidechain": 0,
      "NEO": 30641908.78,
      "Polygon": 1392427.89
    },
    "change_1h": 0.04,
    "change_1d": 2.39,
    "change_7d": -0.31,
    "listedtimeago": "5 months ago",
    "rank": 5
  },
  {
    "id": "132",
    "name": "hBTC",
    "symbol": "hBTC",
    "chain": "Ethereum",
    "audits": "2",
    "category": "Bridge",
    "chains": [
      "Ethereum"
    ],
    "twitter": "HBTC_official",
    "tvl": 276898761.0512417,
    "chainTvls": {
      "Ethereum": 276898761.0512417
    },
    "change_1h": -0.44,
    "change_1d": 5.05,
    "change_7d": 3.43,
    "mcap": 274941164,
    "listedAt": 1623909947,
    "listedtimeago": "1 year ago",
    "rank": 6
  },
  {
    "id": "1981",
    "name": "Orbit Bridge",
    "symbol": "ORC",
    "chain": "Multi-Chain",
    "audits": "2",
    "category": "Bridge",
    "chains": [
      "Ethereum",
      "Ripple",
      "Binance",
      "Klaytn",
      "Heco",
      "Polygon",
      "Celo"
    ],
    "twitter": "Orbit_Chain",
    "forkedFrom": [],
    "oracles": [],
    "listedAt": 1660730289,
    "tvl": 240198389.44844422,
    "chainTvls": {
      "Klaytn": 2067606.7265015102,
      "Binance": 5247170.286385238,
      "Ethereum": 201535604.02888906,
      "Heco": 1725059.939908897,
      "Polygon": 409018.6535699845,
      "Celo": 74.37002413665594,
      "Ripple": 29213855.443165384
    },
    "change_1h": -0.15,
    "change_1d": 3.44,
    "change_7d": 0.7,
    "mcap": 0,
    "listedtimeago": "2 months ago",
    "rank": 7
  },
  {
    "id": "801",
    "name": "cBridge",
    "symbol": "CELR",
    "chain": "Multi-Chain",
    "audits": "2",
    "category": "Bridge",
    "chains": [
      "Ethereum",
      "Binance",
      "Arbitrum",
      "Polygon",
      "Optimism",
      "Avalanche",
      "Fantom",
      "Shiden",
      "Harmony",
      "Aurora",
      "Metis",
      "Boba",
      "Heco",
      "OKExChain",
      "xDai",
      "Celo",
      "Astar",
      "Moonriver",
      "Syscoin",
      "CLV",
      "Oasis",
      "Conflux",
      "Milkomeda",
      "Moonbeam",
      "REI"
    ],
    "twitter": "CelerNetwork",
    "listedAt": 1636307154,
    "tvl": 166301343.38120174,
    "chainTvls": {
      "Optimism": 5805831.110757077,
      "Metis": 212485.68776387715,
      "Moonriver": 0.4368781066249184,
      "Harmony": 1839690.1275510339,
      "CLV": 0,
      "Binance": 16471469.020024814,
      "Ethereum": 109477295.08351475,
      "xDai": 346.31346581801,
      "Astar": 1.9457616889775147,
      "Oasis": 0,
      "Heco": 3007.1132997554705,
      "Shiden": 3168553.942196995,
      "Avalanche": 5695508.383892599,
      "Conflux": 0,
      "Celo": 103.18354372842666,
      "Arbitrum": 10543694.983767912,
      "Fantom": 4962687.822225519,
      "OKExChain": 1160.1314102148121,
      "Milkomeda": 0,
      "Moonbeam": 0,
      "Boba": 69438.22471984767,
      "Aurora": 1728390.854599456,
      "Syscoin": 0.31913,
      "Polygon": 6321678.696698567,
      "REI": 0
    },
    "change_1h": 0.13,
    "change_1d": 1.71,
    "change_7d": 5.46,
    "mcap": 98456141,
    "listedtimeago": "11 months ago",
    "rank": 8
  },
  {
    "id": "117",
    "name": "RenVM",
    "symbol": "REN",
    "chain": "Multi-Chain",
    "audits": "2",
    "category": "Bridge",
    "chains": [
      "Ethereum",
      "Arbitrum",
      "Solana",
      "Polygon",
      "Binance",
      "Avalanche",
      "Fantom",
      "Optimism",
      "Kava"
    ],
    "twitter": "renprotocol",
    "oracles": [],
    "tvl": 152206559.7422729,
    "chainTvls": {
      "Optimism": 17711.26946445,
      "Kava": 6.830791039999999,
      "Binance": 1720795.0196478255,
      "Ethereum": 128922161.30867605,
      "Avalanche": 1572432.3291315972,
      "Polygon": 3549681.139885114,
      "Solana": 7390204.459534661,
      "Arbitrum": 7633541.57803878,
      "Fantom": 1400025.8071034064
    },
    "change_1h": 0.15,
    "change_1d": 4.7,
    "change_7d": 9.01,
    "mcap": 140331104,
    "listedAt": 1623909947,
    "listedtimeago": "1 year ago",
    "rank": 9
  },
  {
    "id": "1556",
    "name": "Terra Bridge",
    "symbol": "-",
    "chain": "Multi-Chain",
    "audits": "0",
    "category": "Bridge",
    "chains": [
      "Ethereum",
      "Binance",
      "Harmony"
    ],
    "oracles": [],
    "forkedFrom": [],
    "twitter": "terra_money",
    "listedAt": 1647460167,
    "tvl": 134722318.3490543,
    "chainTvls": {
      "Binance": 12362970.942435194,
      "Ethereum": 122198195.06232071,
      "Harmony": 161152.34429838826
    },
    "change_1h": 3.87,
    "change_1d": 15.61,
    "change_7d": 4.74,
    "listedtimeago": "7 months ago",
    "rank": 10
  },
  {
    "id": "1054",
    "name": "ChainPort",
    "symbol": "PORTX",
    "chain": "Multi-Chain",
    "audits": "2",
    "category": "Bridge",
    "chains": [
      "Ethereum",
      "Binance",
      "Polygon",
      "Fantom"
    ],
    "twitter": "chain_port",
    "listedAt": 1639946121,
    "tvl": 126824152.69322401,
    "chainTvls": {
      "Binance": 214946.02176600002,
      "Ethereum": 126609206.671458,
      "Polygon": 0,
      "Fantom": 0
    },
    "change_1h": -0.04,
    "change_1d": -0.04,
    "change_7d": -0.04,
    "mcap": 5917621,
    "listedtimeago": "10 months ago",
    "rank": 11
  },
  {
    "id": "2237",
    "name": "Axelar",
    "symbol": "AXL",
    "chain": "Ethereum",
    "audits": "2",
    "category": "Bridge",
    "chains": [
      "Ethereum"
    ],
    "twitter": "axelarcore",
    "forkedFrom": [],
    "oracles": [],
    "listedAt": 1667045416,
    "tvl": 106733091.06866434,
    "chainTvls": {
      "Ethereum": 106733091.06866434
    },
    "change_1h": 0.06,
    "change_1d": 2.55,
    "change_7d": null,
    "mcap": 0,
    "listedtimeago": "6 days ago",
    "rank": 12
  },
  {
    "id": "864",
    "name": "Wrapped BNB",
    "symbol": "BNB",
    "chain": "Binance",
    "audits": "0",
    "category": "Bridge",
    "chains": [
      "Binance"
    ],
    "twitter": null,
    "forkedFrom": [
      "BinanceChain BEPs"
    ],
    "listedAt": 1637348348,
    "tvl": 73017230.94373715,
    "chainTvls": {
      "Binance": 73017230.94373715
    },
    "change_1h": 0.1,
    "change_1d": 4.6,
    "change_7d": 14.51,
    "listedtimeago": "11 months ago",
    "rank": 13
  },
  {
    "id": "1272",
    "name": "ioTube",
    "symbol": "-",
    "chain": "Multi-Chain",
    "audits": "0",
    "category": "Bridge",
    "chains": [
      "IoTeX",
      "Ethereum",
      "Binance",
      "Polygon"
    ],
    "twitter": "iotube_org",
    "listedAt": 1642303801,
    "tvl": 42820970.16805031,
    "chainTvls": {
      "Binance": 3126018.6464454373,
      "IoTeX": 32008484.46039013,
      "Ethereum": 6915668.269883225,
      "Polygon": 770798.7913315189
    },
    "change_1h": -0.15,
    "change_1d": 0.84,
    "change_7d": 3.45,
    "mcap": 0,
    "listedtimeago": "9 months ago",
    "rank": 14
  },
  {
    "id": "1501",
    "name": "Octus Bridge",
    "symbol": "BRIDGE",
    "chain": "Multi-Chain",
    "audits": "1",
    "category": "Bridge",
    "chains": [
      "Everscale",
      "Ethereum",
      "Binance",
      "Polygon",
      "Fantom",
      "Avalanche",
      "Milkomeda"
    ],
    "oracles": [],
    "forkedFrom": [],
    "twitter": "OctusBridge",
    "listedAt": 1646333180,
    "tvl": 21967209.953805,
    "chainTvls": {
      "Milkomeda": 1.220775278911928,
      "Binance": 1473.7506585972496,
      "Ethereum": 1606127.5243795558,
      "Avalanche": 2.037712,
      "Polygon": 17.768395406144695,
      "Fantom": 5.9040023999999995,
      "Everscale": 20359581.747881763
    },
    "change_1h": -0.03,
    "change_1d": 1.44,
    "change_7d": 2.48,
    "mcap": 9250751,
    "listedtimeago": "8 months ago",
    "rank": 15
  },
  {
    "id": "2081",
    "name": "Wan Bridge",
    "symbol": "-",
    "chain": "Multi-Chain",
    "audits": "2",
    "category": "Bridge",
    "chains": [
      "Wanchain",
      "Avalanche",
      "Moonriver",
      "XDC",
      "Ethereum",
      "Binance",
      "CLV",
      "Moonbeam",
      "Polygon",
      "OKExChain"
    ],
    "oracles": [],
    "forkedFrom": [],
    "twitter": "wanchain_org",
    "listedAt": 1662981783,
    "tvl": 10388055.181199005,
    "chainTvls": {
      "Wanchain": 8534898.475565918,
      "OKExChain": 3.9105306216047295,
      "Moonriver": 568766.2112625747,
      "CLV": 19490.275585242944,
      "Moonbeam": 56.865434883599995,
      "Binance": 46936.470562124356,
      "Ethereum": 220312.27402422825,
      "XDC": 220782.4191469152,
      "Avalanche": 776776.8429180803,
      "Polygon": 31.43616841522053
    },
    "change_1h": -0.35,
    "change_1d": 2.25,
    "change_7d": 4.54,
    "listedtimeago": "1 month ago",
    "rank": 16
  },
  {
    "id": "577",
    "name": "Allbridge",
    "symbol": "ABR",
    "chain": "Multi-Chain",
    "audits": "2",
    "category": "Bridge",
    "chains": [
      "Binance",
      "Ethereum",
      "Solana",
      "Celo",
      "Polygon",
      "Avalanche",
      "Fantom",
      "Near",
      "Terra",
      "Heco",
      "Harmony",
      "Fuse",
      "Aurora"
    ],
    "twitter": "Allbridge_io",
    "tvl": 9660692.85151686,
    "chainTvls": {
      "Celo-staking": 8693.077184,
      "Harmony-staking": 4957.269768,
      "Fuse-staking": 1327.025128,
      "Fantom-staking": 27762.661696,
      "Harmony": 0,
      "Near-staking": 6105.221407999999,
      "Terra-staking": 21341.448743999998,
      "Binance": 2331303.102502482,
      "Ethereum": 2274891.0317416363,
      "Heco": 25444.525403039417,
      "Binance-staking": 58313.504568,
      "Avalanche": 668211.2174857062,
      "Celo": 1261912.6200875146,
      "Fuse": 0,
      "Fantom": 167356.55147112074,
      "staking": 445340.43540799996,
      "Aurora-staking": 10215.201831999999,
      "Terra": 73715.83969504,
      "Near": 93810.58,
      "Heco-staking": 908.6063359999999,
      "Solana-staking": 285383.91323199996,
      "Aurora": 0,
      "Avalanche-staking": 8403.911823999999,
      "Polygon": 1174458.419116567,
      "Solana": 1589588.964013754,
      "Polygon-staking": 11928.593687999999
    },
    "change_1h": -0.21,
    "change_1d": 3.03,
    "change_7d": -2.61,
    "staking": 445340.43540799996,
    "mcap": 1609335,
    "listedAt": 1623909947,
    "listedtimeago": "1 year ago",
    "rank": 17
  },
  {
    "id": "1491",
    "name": "RelayChain",
    "symbol": "RELAY",
    "chain": "Multi-Chain",
    "audits": "2",
    "category": "Bridge",
    "chains": [
      "Ethereum",
      "Polygon",
      "Avalanche",
      "Binance",
      "Fantom",
      "Arbitrum",
      "Metis",
      "Optimism",
      "Cronos",
      "Harmony",
      "Heco",
      "Moonriver",
      "IoTeX"
    ],
    "oracles": [],
    "forkedFrom": [],
    "twitter": "relay_chain",
    "listedAt": 1646164456,
    "tvl": 8709583.564966356,
    "chainTvls": {
      "Optimism": 53512.9446713,
      "Metis": 159679.1940516299,
      "Cronos": 43182.45830897711,
      "Moonriver": 1931.6315422861028,
      "Harmony": 17876.67831260776,
      "Binance": 730929.3382500333,
      "IoTeX": 0,
      "Ethereum": 3618365.23305269,
      "Heco": 10668.127958573505,
      "Avalanche": 882946.1670548145,
      "Polygon": 2630651.827154012,
      "Arbitrum": 224210.69993539999,
      "Fantom": 335629.2646740326
    },
    "change_1h": 2.82,
    "change_1d": 11.33,
    "change_7d": 20.21,
    "mcap": 897856,
    "listedtimeago": "8 months ago",
    "rank": 18
  },
  {
    "id": "1578",
    "name": "Hyphen",
    "symbol": "-",
    "chain": "Multi-Chain",
    "audits": "2",
    "category": "Bridge",
    "chains": [
      "Ethereum",
      "Binance",
      "Polygon",
      "Avalanche",
      "Arbitrum",
      "Optimism"
    ],
    "oracles": [],
    "forkedFrom": [],
    "twitter": "biconomy",
    "listedAt": 1648148576,
    "tvl": 4122555.0133480118,
    "chainTvls": {
      "Optimism": 407973.10897680407,
      "Binance": 900845.4738817713,
      "Ethereum": 1018583.3589500666,
      "Avalanche": 574977.8211459557,
      "Polygon": 812143.3686985674,
      "Arbitrum": 408031.88169484667
    },
    "change_1h": -0.17,
    "change_1d": 0.6,
    "change_7d": -7.34,
    "listedtimeago": "7 months ago",
    "rank": 19
  },
  {
    "id": "1885",
    "name": "XY Finance",
    "symbol": "XY",
    "chain": "Multi-Chain",
    "audits": "2",
    "category": "Bridge",
    "chains": [
      "Astar",
      "Klaytn",
      "Ethereum",
      "Binance",
      "Optimism",
      "Fantom",
      "Cronos",
      "Moonriver",
      "Arbitrum",
      "ThunderCore",
      "Kucoin",
      "Polygon",
      "Avalanche"
    ],
    "oracles": [],
    "forkedFrom": [],
    "twitter": "xyfinance",
    "listedAt": 1657208486,
    "tvl": 3647098.3768383646,
    "chainTvls": {
      "Optimism": 348573.3787820788,
      "Cronos": 305259.8107113491,
      "Moonriver": 167813.6108491417,
      "Klaytn": 540985.0594743668,
      "Kucoin": 118809.06757824379,
      "ThunderCore": 152676.5026970212,
      "Binance": 377726.85434999334,
      "Ethereum": 405356.69963294565,
      "Astar": 646249.0693469455,
      "Avalanche": 33557.40752835426,
      "Polygon": 71832.9715863787,
      "Arbitrum": 162868.80363684817,
      "Fantom": 315389.14066469803
    },
    "change_1h": -0.13,
    "change_1d": 0.81,
    "change_7d": 0.42,
    "mcap": 1897938,
    "listedtimeago": "3 months ago",
    "rank": 20
  },
  {
    "id": "2033",
    "name": "Interlay BTC",
    "symbol": "INTR",
    "chain": "Interlay",
    "audits": "0",
    "category": "Bridge",
    "chains": [
      "Interlay"
    ],
    "oracles": [],
    "forkedFrom": [],
    "twitter": "InterlayHQ",
    "parentProtocol": "Interlay",
    "listedAt": 1661801239,
    "tvl": 1812632.4484215502,
    "chainTvls": {
      "Interlay": 1812632.4484215502
    },
    "change_1h": 0.18,
    "change_1d": 5.53,
    "change_7d": 1.34,
    "listedtimeago": "2 months ago",
    "rank": 21
  },
  {
    "id": "1462",
    "name": "deBridge",
    "symbol": "-",
    "chain": "Multi-Chain",
    "audits": "2",
    "category": "Bridge",
    "chains": [
      "Ethereum",
      "Polygon",
      "Binance",
      "Arbitrum",
      "Heco"
    ],
    "oracles": [],
    "forkedFrom": [],
    "twitter": "deBridgeFinance",
    "listedAt": 1645648202,
    "tvl": 1303992.7993373428,
    "chainTvls": {
      "Binance": 11405.146367964031,
      "Ethereum": 1247577.0324406133,
      "Heco": 77.1158430702126,
      "Polygon": 34164.674648787295,
      "Arbitrum": 10768.830036907908
    },
    "change_1h": -0.08,
    "change_1d": 0.98,
    "change_7d": -3.05,
    "listedtimeago": "8 months ago",
    "rank": 22
  },
  {
    "id": "2140",
    "name": "SWFT",
    "symbol": "-",
    "chain": "Multi-Chain",
    "audits": "0",
    "category": "Bridge",
    "chains": [
      "Ethereum",
      "Binance",
      "Heco",
      "OKExChain",
      "Polygon",
      "Fantom",
      "Kava"
    ],
    "oracles": [],
    "forkedFrom": [],
    "twitter": "SWFTBridge",
    "listedAt": 1664544754,
    "tvl": 512822.5446879302,
    "chainTvls": {
      "Kava": 7.4,
      "OKExChain": 64694.57652292053,
      "Binance": 167839.99002321373,
      "Ethereum": 176970.6645537603,
      "Heco": 65644.44513808451,
      "Polygon": 25639.847266618865,
      "Fantom": 12025.62118333228
    },
    "change_1h": 20.29,
    "change_1d": 20.88,
    "change_7d": 3.88,
    "listedtimeago": "1 month ago",
    "rank": 23
  },
  {
    "id": "215",
    "name": "Strudel Finance",
    "symbol": "TRDL",
    "chain": "Ethereum",
    "audits": "0",
    "category": "Bridge",
    "chains": [
      "Ethereum"
    ],
    "twitter": "EnterTheStrudel",
    "tvl": 498378.1813106,
    "chainTvls": {
      "Ethereum": 498378.1813106
    },
    "change_1h": 0.18,
    "change_1d": 5.36,
    "change_7d": 3.22,
    "mcap": 0,
    "listedAt": 1623909947,
    "listedtimeago": "1 year ago",
    "rank": 24
  },
  {
    "id": "1951",
    "name": "DotOracle",
    "symbol": "DTO",
    "chain": "Multi-Chain",
    "audits": "0",
    "category": "Bridge",
    "chains": [
      "Ethereum",
      "Binance",
      "Avalanche",
      "OKExChain",
      "Moonbeam"
    ],
    "oracles": [],
    "forkedFrom": [],
    "twitter": "DoTOracle",
    "listedAt": 1659607635,
    "tvl": 333225.3446611373,
    "chainTvls": {
      "OKExChain": 20.444142758050347,
      "Moonbeam": 5.3139556124805365,
      "Binance": 580.2515283950326,
      "Ethereum": 332598.3305359706,
      "Avalanche": 21.004498401134153,
      "Ethereum-staking": 129085.52123929249,
      "staking": 129085.52123929249
    },
    "change_1h": -0.1,
    "change_1d": 1.79,
    "change_7d": 0.19,
    "staking": 129085.52123929249,
    "mcap": 0,
    "listedtimeago": "3 months ago",
    "rank": 25
  },
  {
    "id": "1996",
    "name": "Glitter Finance",
    "symbol": "XGLI",
    "chain": "Multi-Chain",
    "audits": "2",
    "category": "Bridge",
    "chains": [
      "Solana",
      "Algorand"
    ],
    "twitter": "GlitterFinance",
    "listedAt": 1660945639,
    "tvl": 174565.3407389975,
    "chainTvls": {
      "Algorand": 66092.25671868134,
      "Solana": 108473.08402031616
    },
    "change_1h": -0.85,
    "change_1d": 9.5,
    "change_7d": 8.99,
    "mcap": 0,
    "listedtimeago": "2 months ago",
    "rank": 26
  },
  {
    "id": "2214",
    "name": "BridgeKek",
    "symbol": "-",
    "chain": "Multi-Chain",
    "audits": "0",
    "category": "Bridge",
    "chains": [
      "Kekchain",
      "Ethereum"
    ],
    "twitter": null,
    "forkedFrom": [],
    "oracles": [],
    "listedAt": 1666535695,
    "tvl": 115984.57279330965,
    "chainTvls": {
      "Kekchain": 59695.6390244688,
      "Ethereum": 56288.93376884085
    },
    "change_1h": -0.27,
    "change_1d": 13.85,
    "change_7d": -26.47,
    "listedtimeago": "1 week ago",
    "rank": 27
  },
  {
    "id": "1682",
    "name": "Nomad",
    "symbol": "-",
    "chain": "Multi-Chain",
    "audits": "0",
    "category": "Bridge",
    "chains": [
      "Ethereum",
      "Evmos",
      "Milkomeda",
      "Moonbeam"
    ],
    "oracles": [],
    "forkedFrom": [],
    "twitter": "nomadxyz_",
    "listedAt": 1650917040,
    "tvl": 106862.86891565952,
    "chainTvls": {
      "Ethereum": 106862.86891565952,
      "Evmos": 0,
      "Milkomeda": 0,
      "Moonbeam": 0
    },
    "change_1h": -2.74,
    "change_1d": -6.07,
    "change_7d": 2.67,
    "listedtimeago": "6 months ago",
    "rank": 28
  },
  {
    "id": "1675",
    "name": "CENNZnet Bridge",
    "symbol": "-",
    "chain": "Ethereum",
    "audits": "0",
    "category": "Bridge",
    "chains": [
      "Ethereum"
    ],
    "oracles": [],
    "forkedFrom": [],
    "twitter": "CENNZnet",
    "listedAt": 1650586534,
    "tvl": 94978.1705366349,
    "chainTvls": {
      "Ethereum": 94978.1705366349
    },
    "change_1h": -0.22,
    "change_1d": 6.3,
    "change_7d": 3.52,
    "listedtimeago": "6 months ago",
    "rank": 29
  }
]