[
  {
    "id": "266",
    "name": "Set Protocol",
    "symbol": "-",
    "chain": "Ethereum",
    "audits": "2",
    "category": "Indexes",
    "chains": [
      "Ethereum"
    ],
    "twitter": "SetProtocol",
    "oracles": [
      "Chainlink"
    ],
    "tvl": 58983327.961395,
    "chainTvls": {
      "Ethereum": 58983327.961395
    },
    "change_1h": 0.93,
    "change_1d": -3.92,
    "change_7d": -15.05,
    "listedAt": 1623909947,
    "listedtimeago": "1 year ago",
    "rank": 1
  },
  {
    "id": "172",
    "name": "Index Coop",
    "symbol": "INDEX",
    "chain": "Ethereum",
    "audits": "2",
    "category": "Indexes",
    "chains": [
      "Ethereum"
    ],
    "twitter": "indexcoop",
    "tvl": 43147698.029580586,
    "chainTvls": {
      "Ethereum": 43147698.029580586
    },
    "change_1h": 0.89,
    "change_1d": -4.24,
    "change_7d": -16.05,
    "mcap": 9031180,
    "listedAt": 1623909947,
    "listedtimeago": "1 year ago",
    "rank": 2
  },
  {
    "id": "225",
    "name": "Enzyme Finance",
    "symbol": "MLN",
    "chain": "Ethereum",
    "audits": "2",
    "category": "Indexes",
    "chains": [
      "Ethereum"
    ],
    "twitter": "enzymefinance",
    "oracles": [
      "Chainlink"
    ],
    "tvl": 34709784.00510173,
    "chainTvls": {
      "Ethereum": 34709784.00510173
    },
    "change_1h": 0.85,
    "change_1d": -1.95,
    "change_7d": -7.02,
    "mcap": 27676853,
    "listedAt": 1623909947,
    "listedtimeago": "1 year ago",
    "rank": 3
  },
  {
    "id": "190",
    "name": "dHEDGE",
    "symbol": "DHT",
    "chain": "Multi-Chain",
    "audits": "2",
    "category": "Indexes",
    "chains": [
      "Optimism",
      "Polygon",
      "Ethereum"
    ],
    "twitter": "dHedgeOrg",
    "tvl": 11346526.678864874,
    "chainTvls": {
      "Optimism": 5257351.550843667,
      "Ethereum": 2476807.380033746,
      "Polygon": 3612367.7479874613,
      "Ethereum-staking": 710688.6500862184,
      "staking": 710688.6500862184
    },
    "change_1h": 0.01,
    "change_1d": 1.84,
    "change_7d": -2.52,
    "staking": 710688.6500862184,
    "mcap": 2997757,
    "listedAt": 1623909947,
    "listedtimeago": "1 year ago",
    "rank": 4
  },
  {
    "id": "1881",
    "name": "Toros",
    "symbol": "-",
    "chain": "Multi-Chain",
    "audits": "1",
    "category": "Indexes",
    "chains": [
      "Optimism",
      "Polygon"
    ],
    "oracles": [
      "Chainlink"
    ],
    "forkedFrom": [],
    "twitter": "torosfinance",
    "listedAt": 1657055333,
    "tvl": 5698352.2902691625,
    "chainTvls": {
      "Optimism": 3620177.210807712,
      "Polygon": 2078175.0794614507
    },
    "change_1h": 0.19,
    "change_1d": 4.47,
    "change_7d": -0.47,
    "listedtimeago": "4 months ago",
    "rank": 5
  },
  {
    "id": "750",
    "name": "Fractional Art",
    "symbol": "-",
    "chain": "Ethereum",
    "audits": "0",
    "category": "Indexes",
    "chains": [
      "Ethereum"
    ],
    "twitter": "fractional_art",
    "listedAt": 1635876350,
    "tvl": 1968700.2132968593,
    "chainTvls": {
      "Ethereum": 1968700.2132968593
    },
    "change_1h": 1.34,
    "change_1d": -2.55,
    "change_7d": -13.65,
    "listedtimeago": "1 year ago",
    "rank": 6
  },
  {
    "id": "167",
    "name": "PieDAO",
    "symbol": "DOUGH",
    "chain": "Ethereum",
    "audits": "2",
    "category": "Indexes",
    "chains": [
      "Ethereum"
    ],
    "twitter": "PieDAO_Defi",
    "tvl": 1673581.0407545858,
    "chainTvls": {
      "Ethereum": 1673581.0407545858,
      "Ethereum-staking": 683212.7384504118,
      "staking": 683212.7384504118
    },
    "change_1h": 0.65,
    "change_1d": -1.71,
    "change_7d": -10.57,
    "staking": 683212.7384504118,
    "mcap": 595357,
    "listedAt": 1623909947,
    "listedtimeago": "1 year ago",
    "rank": 7
  },
  {
    "id": "241",
    "name": "PowerPool",
    "symbol": "CVP",
    "chain": "Multi-Chain",
    "audits": "2",
    "category": "Indexes",
    "chains": [
      "Ethereum",
      "Binance"
    ],
    "twitter": "powerpoolcvp",
    "tvl": 868504.1090287699,
    "chainTvls": {
      "Binance": 78667.76230622365,
      "Ethereum": 789836.3467225463
    },
    "change_1h": 0.46,
    "change_1d": -5.84,
    "change_7d": -12.82,
    "mcap": 9992489,
    "listedAt": 1623909947,
    "listedtimeago": "1 year ago",
    "rank": 8
  },
  {
    "id": "272",
    "name": "Cryptex Finance",
    "symbol": "CTX",
    "chain": "Multi-Chain",
    "audits": "2",
    "category": "Indexes",
    "chains": [
      "Ethereum",
      "Optimism"
    ],
    "twitter": "CryptexFinance",
    "oracles": [
      "Chainlink"
    ],
    "tvl": 797761.0486756983,
    "chainTvls": {
      "Optimism": 384.25425486235054,
      "pool2": 106756.2170932508,
      "Ethereum-pool2": 106756.2170932508,
      "Ethereum-treasury": 11901495.89071704,
      "Ethereum": 797376.794420836,
      "Ethereum-staking": 41424.39118006235,
      "treasury": 11901495.89071704,
      "staking": 41424.39118006235
    },
    "change_1h": 0.7,
    "change_1d": -1.63,
    "change_7d": -8.64,
    "staking": 41424.39118006235,
    "pool2": 106756.2170932508,
    "mcap": 8060106,
    "listedAt": 1623909947,
    "listedtimeago": "1 year ago",
    "rank": 9
  },
  {
    "id": "1806",
    "name": "Phuture",
    "symbol": "PHTR",
    "chain": "Multi-Chain",
    "audits": "2",
    "category": "Indexes",
    "chains": [
      "Ethereum",
      "Avalanche"
    ],
    "oracles": [
      "Chainlink",
      "TWAP"
    ],
    "forkedFrom": [],
    "twitter": "phuture_finance",
    "listedAt": 1654508924,
    "tvl": 605992.5307579587,
    "chainTvls": {
      "Ethereum": 405642.64177579567,
      "Avalanche": 200349.88898216301
    },
    "change_1h": 0.39,
    "change_1d": -5.62,
    "change_7d": -7.15,
    "mcap": 562354,
    "listedtimeago": "5 months ago",
    "rank": 10
  },
  {
    "id": "188",
    "name": "Indexed Finance",
    "symbol": "NDX",
    "chain": "Ethereum",
    "audits": "2",
    "category": "Indexes",
    "chains": [
      "Ethereum"
    ],
    "twitter": "ndxfi",
    "tvl": 545733.8070214029,
    "chainTvls": {
      "Ethereum": 545733.8070214029
    },
    "change_1h": 0.1,
    "change_1d": -4.98,
    "change_7d": -17.24,
    "mcap": 78614,
    "listedAt": 1623909947,
    "listedtimeago": "1 year ago",
    "rank": 11
  },
  {
    "id": "250",
    "name": "BasketDAO",
    "symbol": "BASK",
    "chain": "Ethereum",
    "audits": "2",
    "category": "Indexes",
    "chains": [
      "Ethereum"
    ],
    "twitter": "BasketDAOOrg",
    "tvl": 476361.2362391795,
    "chainTvls": {
      "Ethereum": 476361.2362391795
    },
    "change_1h": 0.11,
    "change_1d": 0.16,
    "change_7d": 0.05,
    "mcap": 26030,
    "listedAt": 1623909947,
    "listedtimeago": "1 year ago",
    "rank": 12
  },
  {
    "id": "1914",
    "name": "Pony Finance",
    "symbol": "PONY",
    "chain": "Ethereum",
    "audits": "3",
    "category": "Indexes",
    "chains": [
      "Ethereum"
    ],
    "oracles": [],
    "forkedFrom": [],
    "twitter": "PonyFinance",
    "listedAt": 1658298409,
    "tvl": 402933.21623153554,
    "chainTvls": {
      "Ethereum": 402933.21623153554
    },
    "change_1h": 0,
    "change_1d": 0,
    "change_7d": -2.65,
    "mcap": 404329,
    "listedtimeago": "4 months ago",
    "rank": 13
  },
  {
    "id": "400",
    "name": "Amun",
    "symbol": "AMUN",
    "chain": "Multi-Chain",
    "audits": "2",
    "category": "Indexes",
    "chains": [
      "Polygon",
      "Ethereum",
      "Solana"
    ],
    "twitter": "amun",
    "tvl": 378335.32137200615,
    "chainTvls": {
      "Ethereum": 77793.66850540238,
      "Polygon": 228122.1737417074,
      "Solana": 72419.47912489637
    },
    "change_1h": 0.45,
    "change_1d": 0.04,
    "change_7d": -14.09,
    "mcap": 0,
    "listedAt": 1623909947,
    "listedtimeago": "1 year ago",
    "rank": 14
  },
  {
    "id": "697",
    "name": "Cook Finance",
    "symbol": "COOK",
    "chain": "Multi-Chain",
    "audits": "2",
    "category": "Indexes",
    "chains": [
      "Heco",
      "Binance",
      "Ethereum",
      "Avalanche"
    ],
    "twitter": "cook_finance",
    "listedAt": 1634930710,
    "tvl": 289996.3362189016,
    "chainTvls": {
      "pool2": 3046.9103266003594,
      "Heco-staking": 934.1429048565616,
      "Binance-pool2": 0,
      "Ethereum-pool2": 0,
      "Binance": 157166.7016422084,
      "Ethereum": 101829.25915314937,
      "Binance-staking": 19610.197298550935,
      "Avalanche": 31000.375423543832,
      "Avalanche-staking": 5935.500536379237,
      "Ethereum-staking": 32323.451139893088,
      "Heco-pool2": 3046.9103266003594,
      "Avalanche-pool2": 0,
      "staking": 58803.291879679826
    },
    "change_1h": 0.57,
    "change_1d": 3.68,
    "change_7d": -7.95,
    "staking": 58803.291879679826,
    "pool2": 3046.9103266003594,
    "mcap": 450517,
    "listedtimeago": "1 year ago",
    "rank": 15
  },
  {
    "id": "967",
    "name": "Babylon Finance",
    "symbol": "BABL",
    "chain": "Ethereum",
    "audits": "2",
    "category": "Indexes",
    "chains": [
      "Ethereum"
    ],
    "twitter": "BabylonFinance",
    "listedAt": 1638501613,
    "tvl": 158230.64270802878,
    "chainTvls": {
      "Ethereum": 158230.64270802878,
      "Ethereum-staking": 15.415158022489315,
      "staking": 15.415158022489315
    },
    "change_1h": 0.53,
    "change_1d": -0.81,
    "change_7d": -10.09,
    "staking": 15.415158022489315,
    "mcap": 19297.93,
    "listedtimeago": "11 months ago",
    "rank": 16
  },
  {
    "id": "1771",
    "name": "Arch Ethereum Web3",
    "symbol": "WEB3",
    "chain": "Ethereum",
    "audits": "0",
    "category": "Indexes",
    "chains": [
      "Ethereum"
    ],
    "oracles": [],
    "forkedFrom": [
      "Set Protocol"
    ],
    "twitter": "archdefi",
    "listedAt": 1652988802,
    "tvl": 155175.9298013202,
    "chainTvls": {
      "Ethereum": 155175.9298013202
    },
    "change_1h": 1.34,
    "change_1d": -1.61,
    "change_7d": -15.56,
    "listedtimeago": "6 months ago",
    "rank": 17
  },
  {
    "id": "1358",
    "name": "Kassandra DAO",
    "symbol": "KACY",
    "chain": "Avalanche",
    "audits": "2",
    "category": "Indexes",
    "chains": [
      "Avalanche"
    ],
    "twitter": "dao_kassandra",
    "listedAt": 1643914440,
    "tvl": 106782.7196555708,
    "chainTvls": {
      "Avalanche": 106782.7196555708
    },
    "change_1h": 0.08,
    "change_1d": -0.37,
    "change_7d": -7.13,
    "mcap": 66179,
    "listedtimeago": "9 months ago",
    "rank": 18
  },
  {
    "id": "699",
    "name": "Polly Finance",
    "symbol": "POLLY",
    "chain": "Polygon",
    "audits": "0",
    "category": "Indexes",
    "chains": [
      "Polygon"
    ],
    "twitter": "thebaoman",
    "listedAt": 1634972259,
    "tvl": 105210.84290838378,
    "chainTvls": {
      "Polygon": 105210.84290838378,
      "pool2": 43085.580487710016,
      "Polygon-pool2": 43085.580487710016
    },
    "change_1h": 1.63,
    "change_1d": -3.88,
    "change_7d": -13.27,
    "pool2": 43085.580487710016,
    "mcap": 0,
    "listedtimeago": "1 year ago",
    "rank": 19
  },
  {
    "id": "1537",
    "name": "Solrise Finance",
    "symbol": "SLRS",
    "chain": "Solana",
    "audits": "0",
    "category": "Indexes",
    "chains": [
      "Solana"
    ],
    "oracles": [],
    "forkedFrom": [],
    "twitter": "SolriseFinance",
    "listedAt": 1647034707,
    "tvl": 96553.32779992899,
    "chainTvls": {
      "Solana-staking": 49948.29326887399,
      "Solana": 96553.32779992899,
      "staking": 49948.29326887399
    },
    "change_1h": 0.3,
    "change_1d": -0.46,
    "change_7d": -25.4,
    "staking": 49948.29326887399,
    "mcap": 324692,
    "listedtimeago": "8 months ago",
    "rank": 20
  },
  {
    "id": "1808",
    "name": "Axia Protocol",
    "symbol": "AXIAv3",
    "chain": "Multi-Chain",
    "audits": "2",
    "category": "Indexes",
    "chains": [
      "Ethereum",
      "Polygon"
    ],
    "oracles": [],
    "forkedFrom": [],
    "twitter": "axiaprotocol",
    "listedAt": 1654600878,
    "tvl": 83402.98593923327,
    "chainTvls": {
      "Ethereum": 65253.02787229125,
      "Polygon": 18149.95806694203,
      "Ethereum-staking": 11373.568767366585,
      "Polygon-staking": 6633.491726221541,
      "staking": 18007.060493588127
    },
    "change_1h": 1.27,
    "change_1d": -3.79,
    "change_7d": -16.74,
    "staking": 18007.060493588127,
    "mcap": 20284,
    "listedtimeago": "5 months ago",
    "rank": 21
  },
  {
    "id": "969",
    "name": "DeHive",
    "symbol": "DHV",
    "chain": "Multi-Chain",
    "audits": "2",
    "category": "Indexes",
    "chains": [
      "Ethereum",
      "Binance",
      "xDai",
      "Polygon"
    ],
    "twitter": "dehive_finance",
    "listedAt": 1638565180,
    "tvl": 80741.64783852482,
    "chainTvls": {
      "pool2": 14666.938106674257,
      "Polygon-pool2": 5277.562564833753,
      "xDai-pool2": 3739.518621340894,
      "Binance-pool2": 5644.442060385621,
      "Ethereum-pool2": 5.4148601139894055,
      "Binance": 31659.940569487477,
      "Ethereum": 36261.74200785765,
      "xDai": 7542.40269634595,
      "Binance-staking": 11872.63466875135,
      "Ethereum-staking": 12991.31453620937,
      "Polygon": 5277.562564833754,
      "Polygon-staking": 12198.83200052177,
      "xDai-staking": 2882.2136836833015,
      "staking": 39944.99488916579
    },
    "change_1h": 0.44,
    "change_1d": -0.88,
    "change_7d": -9.89,
    "staking": 39944.99488916579,
    "pool2": 14666.938106674257,
    "mcap": 227720,
    "listedtimeago": "11 months ago",
    "rank": 22
  },
  {
    "id": "1421",
    "name": "Enso Finance",
    "symbol": "-",
    "chain": "Ethereum",
    "audits": "0",
    "category": "Indexes",
    "chains": [
      "Ethereum"
    ],
    "oracles": [],
    "forkedFrom": [],
    "twitter": "EnsoFinance",
    "listedAt": 1645036681,
    "tvl": 55596.22883570663,
    "chainTvls": {
      "Ethereum": 55596.22883570663
    },
    "change_1h": 0.2,
    "change_1d": 0.15,
    "change_7d": -8.58,
    "listedtimeago": "9 months ago",
    "rank": 23
  },
  {
    "id": "1836",
    "name": "Investin",
    "symbol": "IVN",
    "chain": "Solana",
    "audits": "0",
    "category": "Indexes",
    "chains": [
      "Solana"
    ],
    "oracles": [
      "Pyth"
    ],
    "forkedFrom": [],
    "twitter": "Investin_pro",
    "listedAt": 1655548694,
    "tvl": 25075,
    "chainTvls": {
      "Solana": 25075
    },
    "change_1h": 0.11,
    "change_1d": -0.36,
    "change_7d": -5.33,
    "mcap": 79073,
    "listedtimeago": "5 months ago",
    "rank": 24
  },
  {
    "id": "725",
    "name": "BiShares",
    "symbol": "BISON",
    "chain": "Multi-Chain",
    "audits": "2",
    "category": "Indexes",
    "chains": [
      "Binance",
      "Fantom"
    ],
    "twitter": "BiSharesFinance",
    "forkedFrom": [
      "Indexed Finance"
    ],
    "listedAt": 1635467248,
    "tvl": 10833.543661843853,
    "chainTvls": {
      "Binance": 10478.603166569075,
      "Fantom": 354.940495274777
    },
    "change_1h": 0.73,
    "change_1d": -1.45,
    "change_7d": -10.86,
    "mcap": 10139.92,
    "listedtimeago": "1 year ago",
    "rank": 25
  },
  {
    "id": "1603",
    "name": "Picnic",
    "symbol": "-",
    "chain": "Polygon",
    "audits": "2",
    "category": "Indexes",
    "chains": [
      "Polygon"
    ],
    "oracles": [],
    "forkedFrom": [],
    "twitter": "usePicnic",
    "listedAt": 1648841682,
    "tvl": 8227.643402258116,
    "chainTvls": {
      "Polygon": 8227.643402258116
    },
    "change_1h": 0.44,
    "change_1d": -0.35,
    "change_7d": -2.97,
    "listedtimeago": "7 months ago",
    "rank": 26
  },
  {
    "id": "819",
    "name": "Helios Prime",
    "symbol": "-",
    "chain": "Ethereum",
    "audits": "0",
    "category": "Indexes",
    "chains": [
      "Ethereum"
    ],
    "twitter": "HeliosPrimeOne",
    "listedAt": 1636448140,
    "tvl": 1987.25476854809,
    "chainTvls": {
      "Ethereum": 1987.25476854809
    },
    "change_1h": 0.49,
    "change_1d": 1.8,
    "change_7d": -11.46,
    "listedtimeago": "1 year ago",
    "rank": 27
  }
]