[
  {
    "category": "Dexes",
    "tvl": 24771088109.587315,
    "percentage": 27.08,
    "count": 502,
    "rank": 1
  },
  {
    "category": "Lending",
    "tvl": 16114560721.731998,
    "percentage": 17.62,
    "count": 155,
    "rank": 2
  },
  {
    "category": "Bridge",
    "tvl": 11451388988.291643,
    "percentage": 12.52,
    "count": 26,
    "rank": 3
  },
  {
    "category": "CDP",
    "tvl": 10624565210.45955,
    "percentage": 11.61,
    "count": 47,
    "rank": 4
  },
  {
    "category": "Liquid Staking",
    "tvl": 9022407586.218359,
    "percentage": 9.86,
    "count": 35,
    "rank": 5
  }
]